midjourney/__init__.py
midjourney/decrypt.py
midjourney/index.py
midjourney/irequest.py
midjourney_py-1.0.4.dist-info/METADATA
midjourney_py-1.0.4.dist-info/WHEEL
midjourney_py-1.0.4.dist-info/top_level.txt
midjourney_py-1.0.4.dist-info/RECORD
