Metadata-Version: 2.1
Name: midjourney-py
Version: 1.0.4
Summary: MidjourneyPy allows developers to easily use midjourney api without complications.
Home-page: UNKNOWN
Author: Ajaga Abdulbasit (Code  Ninja)
Author-email: basitng2004@gmail.com
License: UNKNOWN
Keywords: python,ai,midjourney,image,request,stable,stable difusion,difusion
Platform: UNKNOWN
Classifier: Development Status :: 1 - Planning
Classifier: Intended Audience :: Developers
Classifier: Programming Language :: Python :: 3
Classifier: Operating System :: Unix
Classifier: Operating System :: MacOS :: MacOS X
Classifier: Operating System :: Microsoft :: Windows
Requires-Dist: requests
